airdialogue/__init__.py
airdialogue/context_generator/__init__.py
airdialogue/context_generator/context_generator_lib.py
airdialogue/context_generator/context_generator_main.py
airdialogue/context_generator/src/__init__.py
airdialogue/context_generator/src/customer.py
airdialogue/context_generator/src/facts.py
airdialogue/context_generator/src/kb.py
airdialogue/context_generator/src/utils.py
airdialogue/evaluator/__init__.py
airdialogue/evaluator/evaluator_main.py
airdialogue/evaluator/infer_utils.py
airdialogue/evaluator/selfplay_utils.py
airdialogue/evaluator/metrics/__init__.py
airdialogue/evaluator/metrics/bleu.py
airdialogue/evaluator/metrics/f1.py
airdialogue/evaluator/metrics/flight_distance.py
airdialogue/evaluator/metrics/kl.py
airdialogue/evaluator/metrics/rouge.py
airdialogue/generate_infer/__init__.py
airdialogue/generate_infer/generate_infer_main.py
airdialogue/prepro/__init__.py
airdialogue/prepro/prepro_main.py
airdialogue/prepro/standardize_data_lib.py
airdialogue/prepro/tokenize_lib.py
airdialogue/simulator/__init__.py
airdialogue/simulator/interaction.py
airdialogue/simulator/simulator_main.py
airdialogue/visualizer/__init__.py
airdialogue/visualizer/utils.py
airdialogue/visualizer/visualizer_main.py
airdialogue_essentials-0.1.data/scripts/airdialogue
airdialogue_essentials-0.1.dist-info/LICENSE
airdialogue_essentials-0.1.dist-info/METADATA
airdialogue_essentials-0.1.dist-info/WHEEL
airdialogue_essentials-0.1.dist-info/top_level.txt
airdialogue_essentials-0.1.dist-info/RECORD
