Metadata-Version: 2.1
Name: airdialogue-essentials
Version: 0.1
Summary: airdialogue package
Home-page: https://github.com/javatechy/dokr
Author: Wei Wei
Author-email: wewei@google.com
License: UNKNOWN
Platform: UNKNOWN
Classifier: Programming Language :: Python :: 2
Classifier: License :: OSI Approved :: MIT License
Classifier: Operating System :: OS Independent
License-File: LICENSE
Requires-Dist: tqdm
Requires-Dist: nltk
Requires-Dist: flask
